celulartable/__init__.py
celulartable/table.py
celulartable/cell/__init__.py
celulartable/cell/cell.py
celulartable/cell/cell_rows.py
celulartable/cell/cell_styles.py
celulartable/core/__init__.py
celulartable/core/table.py
celulartable/type_checking/__init__.py
celulartable/type_checking/cell_parsing.py
celulartable/type_checking/column_parsing.py
celulartable/type_checking/type_parsers.py
celulartable/utils/__init__.py
celulartable/utils/constants.py
celulartable/utils/micro_classes.py
celulartable-0.0.1.data/data/LICENSE
celulartable-0.0.1.dist-info/LICENSE
celulartable-0.0.1.dist-info/LICENSE.txt
celulartable-0.0.1.dist-info/METADATA
celulartable-0.0.1.dist-info/WHEEL
celulartable-0.0.1.dist-info/top_level.txt
celulartable-0.0.1.dist-info/RECORD
