Metadata-Version: 2.1
Name: celulartable
Version: 0.0.1
Summary: Tables made of cells for console.
Home-page: https://github.com/Kyostenas/celulartable
Download-URL: 
Author: Kyostenas
Author-email: kyostenas@gmail.com
License: MIT
Keywords: console,table,cell
Classifier: Development Status :: 3 - Alpha
Classifier: Intended Audience :: Developers
Classifier: Topic :: Software Development :: Build Tools
Classifier: License :: OSI Approved :: MIT License
Classifier: Programming Language :: Python :: 3.8
License-File: LICENSE
License-File: LICENSE.txt
